apollo/__init__.py
apollo/agent.py
apollo/info.py
apollo/version.py
apollo/config/__init__.py
apollo/config/const.py
apollo/config/instructions.py
apollo/service/__init__.py
apollo/service/session.py
apollo/service/tool/__init__.py
apollo/service/tool/executor.py
apollo/service/tool/format.py
apollo/tools/__init__.py
apollo/tools/core.py
apollo/tools/files.py
apollo/tools/search.py
apollo/tools/web.py
apollo_agent-0.4.2.dist-info/licenses/LICENSE.txt
apollo_agent-0.4.2.dist-info/METADATA
apollo_agent-0.4.2.dist-info/WHEEL
apollo_agent-0.4.2.dist-info/entry_points.txt
apollo_agent-0.4.2.dist-info/top_level.txt
apollo_agent-0.4.2.dist-info/RECORD
