Metadata-Version: 2.4
Name: apollo-agent
Version: 0.4.2
Summary: A custom AI agent that implements various functions for code assistance
Home-page: https://github.com/AlbertoBarrago/Apollo-Agent
Author: Alberto Barrago
Author-email: albertobarrago@gmail.com
Classifier: Programming Language :: Python :: 3
Classifier: License :: OSI Approved :: BSD License
Classifier: Operating System :: OS Independent
Classifier: Development Status :: 3 - Alpha
Requires-Python: >=3.10
License-File: LICENSE.txt
Requires-Dist: requests>=2.32.0
Requires-Dist: ollama~=0.4.8
Requires-Dist: beautifulsoup4>=4.12.0
Requires-Dist: httpx~=0.28.1
Requires-Dist: aiofiles~=24.1.0
Requires-Dist: thefuzz>=0.20.0
Provides-Extra: dev
Requires-Dist: black~=25.1.0; extra == "dev"
Requires-Dist: pytest~=8.3.5; extra == "dev"
Requires-Dist: pytest-cov~=6.1.1; extra == "dev"
Requires-Dist: pytest-asyncio>=0.23.5; extra == "dev"
Dynamic: author
Dynamic: author-email
Dynamic: classifier
Dynamic: description
Dynamic: description-content-type
Dynamic: home-page
Dynamic: license-file
Dynamic: provides-extra
Dynamic: requires-dist
Dynamic: requires-python
Dynamic: summary
